hebing/__init__.py
hebing-0.0.5.dist-info/METADATA
hebing-0.0.5.dist-info/WHEEL
hebing-0.0.5.dist-info/entry_points.txt
hebing-0.0.5.dist-info/top_level.txt
hebing-0.0.5.dist-info/RECORD
